django_quagga-0.6.1.dist-info/DESCRIPTION.rst
django_quagga-0.6.1.dist-info/METADATA
django_quagga-0.6.1.dist-info/RECORD
django_quagga-0.6.1.dist-info/WHEEL
django_quagga-0.6.1.dist-info/metadata.json
django_quagga-0.6.1.dist-info/top_level.txt
zebra/__init__.py
zebra/admin.py
zebra/apps.py
zebra/forms.py
zebra/mixins.py
zebra/models.py
zebra/signals.py
zebra/urls.py
zebra/utils.py
zebra/views.py
zebra/widgets.py
zebra/conf/__init__.py
zebra/conf/options.py
zebra/management/__init__.py
zebra/management/commands/__init__.py
zebra/management/commands/clear_stripe_test_customers.py
zebra/static/zebra/card-form.css
zebra/static/zebra/card-form.js
zebra/templates/zebra/_basic_card_form.html
zebra/templates/zebra/_stripe_js_and_set_stripe_key.html
zebra/templatetags/__init__.py
zebra/templatetags/zebra_tags.py
zebra_sample_project/__init__.py
zebra_sample_project/manage.py
zebra_sample_project/settings.py
zebra_sample_project/urls.py
zebra_sample_project/marty/__init__.py
zebra_sample_project/marty/models.py
zebra_sample_project/marty/tests.py
zebra_sample_project/marty/urls.py
zebra_sample_project/marty/views.py
zebra_sample_project/marty/templates/marty/base.html
zebra_sample_project/marty/templates/marty/basic_update.html
