Metadata-Version: 2.0
Name: django-quagga
Version: 0.6.1
Summary: Library for Django and Stripe
Home-page: https://github.com/bennylope/django-quagga
Author: Ben Lopatin
Author-email: ben@benlopatin.com
License: UNKNOWN
Platform: UNKNOWN
Classifier: Programming Language :: Python
Classifier: License :: OSI Approved :: MIT License
Classifier: Operating System :: OS Independent
Classifier: Development Status :: 4 - Beta
Classifier: Environment :: Web Environment
Classifier: Framework :: Django
Classifier: Intended Audience :: Developers
Classifier: Topic :: Internet :: WWW/HTTP
Classifier: Topic :: Software Development :: Libraries :: Python Modules
Requires-Dist: stripe (>=1.0.0)
